README.md
setup.py
com_gongzhidao_inroad.egg-info/PKG-INFO
com_gongzhidao_inroad.egg-info/SOURCES.txt
com_gongzhidao_inroad.egg-info/dependency_links.txt
com_gongzhidao_inroad.egg-info/top_level.txt
inroad/__init__.py
inroad/element.py
inroad/inroad.py