Metadata-Version: 2.1
Name: com-gongzhidao-inroad
Version: 0.0.1
Summary: 工智道公共方法
Home-page: UNKNOWN
License: UNKNOWN
Platform: UNKNOWN
